{
  "meta": {
    "run_at_tw": "2026-03-27 04:36:10",
    "query": {
      "year": "115",
      "month": "3",
      "day": "27"
    },
    "keywords": [
      "買回公司股份",
      "私募普通股",
      "自結合併",
      "廠務設備",
      "機器設備",
      "現金增資",
      "資本支出",
      "公司債",
      "庫藏股"
    ],
    "matched_count": 6,
    "new_matched_count": 0
  },
  "items": [
    {
      "key": "1150326|sii|6806|1",
      "speech_date": "115/03/26",
      "speech_time": "18:11:14",
      "company_id": "6806",
      "company_name": "森崴能源",
      "subject": "公告本公司修訂國內第一次有擔保轉換公司債發行及轉換辦法業經金融監督管理委員會核准。",
      "matched_keywords": [
        "公司債"
      ],
      "detail_params": {
        "enterDate": "1150326",
        "serialNumber": 1,
        "companyId": "6806",
        "marketKind": "sii"
      },
      "detail": {
        "code": 200,
        "message": "查詢成功",
        "result": {
          "marketName": "上市公司",
          "companyId": "6806",
          "data": [
            [
              1,
              "115/03/26",
              "18:11:14",
              "李心美",
              "財務長",
              "(02)2269-9888",
              "公告本公司修訂國內第一次有擔保轉換公司債發行及轉換辦法\r\n業經金融監督管理委員會核准。",
              "51",
              "115/03/26",
              "1.事實發生日:115/03/26\n2.公司名稱:森崴能源股份有限公司\n3.與公司關係(請輸入本公司或子公司):本公司\n4.相互持股比例:不適用\n5.發生緣由:本公司依據金融監督管理委員會114年5月5日金管證發字\n第1140382105號函規定，修訂「國內第一次有擔保轉換公司債發行及轉換辦法」\n案，業經金融監督管理委員會115年03月25日金管證發字\n第1150337748號函核准在案。\n6.因應措施:無\n7.其他應敘明事項(若事件發生或決議之主體係屬公開發行以上公司，本則重大訊息同時\n  符合證券交易法施行細則第7條第9款所定對股東權益或證券價格有重大影響之事項):\n核准之修訂條文對照內容，請參閱本公司115年03月13日發布之重大訊息，\n核准後完整之「國內第一次有擔保轉換公司債發行及轉換辦法」\n請至公開資訊觀測站「債券發行資訊查詢」。"
            ]
          ],
          "footer": [
            "以上資料均由各公司依發言當時所屬市場別之規定申報後，由本系統對外公佈，資料如有虛偽不實，均由該公司負責。"
          ],
          "header": {
            "note": [],
            "subTitle": [],
            "mainTitle": [
              "公司當日重大訊息之詳細內容"
            ]
          },
          "titles": [
            {
              "main": "序號",
              "sub": []
            },
            {
              "main": "發言日期",
              "sub": []
            },
            {
              "main": "發言時間",
              "sub": []
            },
            {
              "main": "發言人",
              "sub": []
            },
            {
              "main": "發言人職稱",
              "sub": []
            },
            {
              "main": "發言人電話",
              "sub": []
            },
            {
              "main": "主旨",
              "sub": []
            },
            {
              "main": "符合條款",
              "sub": []
            },
            {
              "main": "事實發生日",
              "sub": []
            },
            {
              "main": "說明",
              "sub": []
            }
          ],
          "companyAbbreviation": "森崴能源"
        },
        "datetime": "115/03/27 04:36:11"
      },
      "fetched_at_tw": "2026-03-27 04:36:10"
    },
    {
      "key": "1150326|sii|5871|2",
      "speech_date": "115/03/26",
      "speech_time": "19:18:46",
      "company_id": "5871",
      "company_name": "中租-KY",
      "subject": "代子公司中租迪和公告決議參與認購南山人壽保險累積次順位普通公司債,交易累積金額達NTD334,000,000元",
      "matched_keywords": [
        "公司債"
      ],
      "detail_params": {
        "enterDate": "1150326",
        "serialNumber": 2,
        "companyId": "5871",
        "marketKind": "sii"
      },
      "detail": {
        "code": 200,
        "message": "查詢成功",
        "result": {
          "marketName": "上市公司",
          "companyId": "5871",
          "data": [
            [
              2,
              "115/03/26",
              "19:18:46",
              "廖英智",
              "執行副總經理",
              "02-87526388",
              "代子公司中租迪和公告決議參與認購南山人壽保險\r\n累積次順位普通公司債,交易累積金額達NTD334,000,000元",
              "20",
              "115/03/26",
              "1.標的物之名稱及性質（屬特別股者，並應標明特別股約定發行條件，如股息率等）:\r\n南山人壽保險股份有限公司十年(含)期以上累積次順位普通公司債\r\n2.事實發生日:115/3/26~115/3/26\r\n3.董事會通過日期: 民國115年3月26日\r\n4.其他核決日期: 不適用\r\n5.交易數量、每單位價格及交易總金額:\r\n交易單位數量：將依發行公司公開說明書計算後決定\n每單位價格：按發行價格認購\n交易總金額：以不超過新台幣2.04億元為上限\r\n6.交易相對人及其與公司之關係（交易相對人如屬自然人，且非公司之\r\n關係人者，得免揭露其姓名）:\r\n富邦綜合證券股份有限公司\n非關係人\r\n7.交易相對人為關係人者，並應公告選定關係人為交易對象之原因及前次移\r\n轉之所有人、前次移轉之所有人與公司及交易相對人間相互之關係、前次\r\n移轉日期及移轉金額:\r\n非關係人，不適用\r\n8.交易標的最近五年內所有權人曾為公司之關係人者，尚應公告關係人之取\r\n得及處分日期、價格及交易當時與公司之關係:\r\n不適用\r\n9.本次係處分債權之相關事項（含處分之債權附隨擔保品種類、處分債權\r\n如有屬對關係人債權者尚需公告關係人名稱及本次處分該關係人之債權\r\n帳面金額:\r\n不適用\r\n10.處分利益（或損失）（取得有價證券者不適用）（原遞延者應列表說明\r\n認列情形）:\r\n不適用\r\n11.交付或付款條件（含付款期間及金額）、契約限制條款及其他重要約定\r\n事項:\r\n交付或付款條件：於交割日一次付清。\n契約限制條款及其他重要約定事項：依發行公司之公開說明書所載。\r\n12.本次交易之決定方式、價格決定之參考依據及決策單位:\r\n依子公司中租迪和(股)公司取得或處分相關作業程序之規定，\n提報董事會決議通過，於不超過新台幣2.04億元範圍內，\n授權董事長依市場價格辦理之。\r\n13.取得或處分有價證券標的公司每股淨值:\r\n不適用\r\n14.迄目前為止，累積持有本交易證券（含本次交易）之數量、金額、持股\r\n比例及權利受限情形（如質押情形）:\r\n累積持有數量：30張(112年度第2期)、30張(113年度第1期)、\n30張(114年度第1期)、100張(114年度第3期)、200張(115年度第1期)\n累計投資金額：新台幣394,000仟元\n權利受限情形：無\r\n15.迄目前為止，依「公開發行公司取得或處分資產處理準則」第三條所列\r\n之有價證券投資（含本次交易）占公司最近期財務報表中總資產及歸屬\r\n於母公司業主之權益之比例暨最近期財務報表中營運資金數額（註二）:\r\n占總資產之比例：78.89% ;\n占股東權益之比例：86.97% ; \n最近期財務報表中營運資金數額：新台幣-5,324,943,505元\r\n16.經紀人及經紀費用:\r\n無\r\n17.取得或處分之具體目的或用途:\r\n業務投資\r\n18.本次交易表示異議董事之意見:\r\n無\r\n19.本次交易為關係人交易:否\r\n20.監察人承認或審計委員會同意日期:\r\n不適用\r\n21.本次交易會計師出具非合理性意見:不適用\r\n22.會計師事務所名稱:\r\n不適用\r\n23.會計師姓名:\r\n不適用\r\n24.會計師開業證書字號:\r\n不適用\r\n25.是否涉及營運模式變更:否\r\n26.營運模式變更說明:\r\n無\r\n27.過去一年及預計未來一年內與交易相對人交易情形:\r\n不適用\r\n28.資金來源:\r\n不適用\r\n29.前已就同一件事件發布重大訊息日期: 不適用\r\n30.其他敘明事項:\r\n本次交易上限為NTD204,000,000元，一年內累積金額達NTD334,000,000元。"
            ]
          ],
          "footer": [
            "以上資料均由各公司依發言當時所屬市場別之規定申報後，由本系統對外公佈，資料如有虛偽不實，均由該公司負責。"
          ],
          "header": {
            "note": [],
            "subTitle": [],
            "mainTitle": [
              "公司當日重大訊息之詳細內容"
            ]
          },
          "titles": [
            {
              "main": "序號",
              "sub": []
            },
            {
              "main": "發言日期",
              "sub": []
            },
            {
              "main": "發言時間",
              "sub": []
            },
            {
              "main": "發言人",
              "sub": []
            },
            {
              "main": "發言人職稱",
              "sub": []
            },
            {
              "main": "發言人電話",
              "sub": []
            },
            {
              "main": "主旨",
              "sub": []
            },
            {
              "main": "符合條款",
              "sub": []
            },
            {
              "main": "事實發生日",
              "sub": []
            },
            {
              "main": "說明",
              "sub": []
            }
          ],
          "companyAbbreviation": "中租-KY"
        },
        "datetime": "115/03/27 04:36:12"
      },
      "fetched_at_tw": "2026-03-27 04:36:10"
    },
    {
      "key": "1150326|otc|6821|4",
      "speech_date": "115/03/26",
      "speech_time": "18:04:24",
      "company_id": "6821",
      "company_name": "聯寶",
      "subject": "更正本公司115年03月26日重大訊息「公告本公司國內第一次無擔保轉換公司債停止受理轉(交)換等相關事項」之停止受理轉(交)換事由",
      "matched_keywords": [
        "公司債"
      ],
      "detail_params": {
        "enterDate": "1150326",
        "serialNumber": 4,
        "companyId": "6821",
        "marketKind": "otc"
      },
      "detail": {
        "code": 200,
        "message": "查詢成功",
        "result": {
          "marketName": "上櫃公司",
          "companyId": "6821",
          "data": [
            [
              4,
              "115/03/26",
              "18:04:24",
              "譚偉傑",
              "總經理",
              "02-8919-1380",
              "更正本公司115年03月26日重大訊息\r\n「公告本公司國內第一次無擔保轉換公司債停止受理轉(交)換\r\n等相關事項」之停止受理轉(交)換事由",
              "53",
              "115/03/26",
              "1.事實發生日:115/03/26\n2.公司名稱:聯寶電子股份有限公司\n3.與公司關係(請輸入本公司或子公司):本公司\n4.相互持股比例:不適用\n5.發生緣由:本公司於115年03月26日公告國內第一次無擔保轉換公司債\n（簡稱：聯寶一，代碼：68211）停止受理轉(交)換等相關事項，\n其中「停止受理轉(交)換之事由」誤植，爰予以更正。\n6.更正資訊項目/報表名稱:停止受理轉(交)換之事由\n7.更正前金額/內容/頁次:\n原公告停止受理轉(交)換之事由為：「辦理股東常會等事宜」。\n8.更正後金額/內容/頁次:\n停止受理轉(交)換之事由更正為：「因配合除息停止過戶作業，\n依相關規定停止受理轉(交)換」。\n9.因應措施:發布重大訊息更正。\n10.其他應敘明事項:無。"
            ]
          ],
          "footer": [
            "以上資料均由各公司依發言當時所屬市場別之規定申報後，由本系統對外公佈，資料如有虛偽不實，均由該公司負責。"
          ],
          "header": {
            "note": [],
            "subTitle": [],
            "mainTitle": [
              "公司當日重大訊息之詳細內容"
            ]
          },
          "titles": [
            {
              "main": "序號",
              "sub": []
            },
            {
              "main": "發言日期",
              "sub": []
            },
            {
              "main": "發言時間",
              "sub": []
            },
            {
              "main": "發言人",
              "sub": []
            },
            {
              "main": "發言人職稱",
              "sub": []
            },
            {
              "main": "發言人電話",
              "sub": []
            },
            {
              "main": "主旨",
              "sub": []
            },
            {
              "main": "符合條款",
              "sub": []
            },
            {
              "main": "事實發生日",
              "sub": []
            },
            {
              "main": "說明",
              "sub": []
            }
          ],
          "companyAbbreviation": "聯寶"
        },
        "datetime": "115/03/27 04:36:13"
      },
      "fetched_at_tw": "2026-03-27 04:36:10"
    },
    {
      "key": "1150326|rotc|6920|7",
      "speech_date": "115/03/26",
      "speech_time": "19:46:18",
      "company_id": "6920",
      "company_name": "恆勁科技",
      "subject": "公告本公司董事會決議辦理私募普通股案",
      "matched_keywords": [
        "私募普通股"
      ],
      "detail_params": {
        "enterDate": "1150326",
        "serialNumber": 7,
        "companyId": "6920",
        "marketKind": "rotc"
      },
      "detail": {
        "code": 200,
        "message": "查詢成功",
        "result": {
          "marketName": "興櫃公司",
          "companyId": "6920",
          "data": [
            [
              7,
              "115/03/26",
              "19:46:18",
              "許詩濱",
              "營運長",
              "(03)598-5778",
              "公告本公司董事會決議辦理私募普通股案",
              "9",
              "115/03/26",
              "1.董事會決議日期:115/03/26\n2.私募有價證券種類:普通股\n3.私募對象及其與公司間關係:\n本次私募普通股之對象以符合「證券交易法」第43條之6及金融監督管理委員會\n112年9月12日金管證發字第1120383220號令規定之特定人為限，\n目前擬洽定之應募人暫訂以內部人、關係人及可能參與\n應募之策略性投資人為主，惟目前尚無已洽定之應募人。\n4.私募股數或張數:不超過50,000,000股為限。\n5.得私募額度:\n本次私募之普通股自股東會決議之日起一年內\n授權董事會全數或分二次辦理，\n合計總發行股數以不超過50,000,000股為限。\n6.私募價格訂定之依據及合理性:\n(1)本次私募普通股價格之訂定，以不低於參考價格之八成\n為訂定私募價格之依據，參考價格為下列二基準計算價格孰高者定之：\n(a)定價日前30個營業日興櫃股票電腦議價點選系統內\n本公司普通股之每一營業日成交金額之總和\n除以每一營業日成交股數之總和計算，\n並扣除無償配股除權及配息，暨加回減資反除權後之股價。\n(b)定價日前最近期經會計師查核簽證或核閱之財務報告顯示之每股淨值。\n(2)本次私募實際發行價格不得低於股票面額，\n實際定價日及實際私募價格於不低於股東會決議成數之範圍內\n授權董事會視日後洽特定人及市場狀況決定之。\n(3)私募價格之定價係遵循主管機關發布之相關法令定之，\n同時考量證券交易法對私募有價證券有三年轉讓限制、公司營運情況、\n未來展望及普通股市價而定，應具有合理性。\n7.本次私募資金用途:充實營運資金、健全財務結構或\n支應其他因應本公司長期發展之資金需求，以改善公司財務結構並強化競爭力。\n8.不採用公開募集之理由:為因應公司長期發展所需而引進之策略性合作夥伴，\n考量私募方式具有籌資迅速簡便之時效性且有限制轉讓之規定，\n較可確保長期營運發展，故不採用公開募集，擬以私募方式辦理增資。\n9.獨立董事反對或保留意見:無。\n10.實際定價日:俟股東會決議通過後授權董事會決定之。\n11.參考價格:俟股東會決議通過後授權董事會決定之。\n12.實際私募價格、轉換或認購價格:俟股東會決議通過後授權董事會決定之。\n13.本次私募新股之權利義務:\n與本公司已發行之普通股相同，惟依證券交易法第 43 條之 8 規定，\n本次私募之普通股於交付日起三年內，除依「證券交易法」第43條之8規定\n之轉讓對象外，不得自由轉讓。本公司擬於交付日起滿三年後，\n依相關法令規定，授權董事會向主管機關補辦公開發行程序暨申請掛牌交易。\n14.附有轉換、交換或認股者，其換股基準日:不適用。\n15.附有轉換、交換或認股者，對股權可能稀釋情形:不適用。\n16.其他應敘明事項:\n本次私募計畫之主要內容，除私募定價成數外，\n包括但不限於實際發行股數、發行價格、發行條件、\n募集金額、計畫項目、預計資金運用進度、應募人之選擇、\n預計可能產生之效益及其他相關未盡事宜，未來如因法令修改、\n或依主管機關規定、或基於營運評估、客觀環境之影響而需變更或修正時，\n擬請授權董事會得依當時市場狀況全權處理之。"
            ]
          ],
          "footer": [
            "以上資料均由各公司依發言當時所屬市場別之規定申報後，由本系統對外公佈，資料如有虛偽不實，均由該公司負責。"
          ],
          "header": {
            "note": [],
            "subTitle": [],
            "mainTitle": [
              "公司當日重大訊息之詳細內容"
            ]
          },
          "titles": [
            {
              "main": "序號",
              "sub": []
            },
            {
              "main": "發言日期",
              "sub": []
            },
            {
              "main": "發言時間",
              "sub": []
            },
            {
              "main": "發言人",
              "sub": []
            },
            {
              "main": "發言人職稱",
              "sub": []
            },
            {
              "main": "發言人電話",
              "sub": []
            },
            {
              "main": "主旨",
              "sub": []
            },
            {
              "main": "符合條款",
              "sub": []
            },
            {
              "main": "事實發生日",
              "sub": []
            },
            {
              "main": "說明",
              "sub": []
            }
          ],
          "companyAbbreviation": "恆勁科技"
        },
        "datetime": "115/03/27 04:36:14"
      },
      "fetched_at_tw": "2026-03-27 04:36:10"
    },
    {
      "key": "1150326|rotc|6748|6",
      "speech_date": "115/03/26",
      "speech_time": "19:46:48",
      "company_id": "6748",
      "company_name": "亞果生醫",
      "subject": "公告本公司董事會通過擬辦理現金增資供初次上市(櫃)或臺灣創新板有價證券之上市前公開承銷暨原股東全數放棄認購案",
      "matched_keywords": [
        "現金增資"
      ],
      "detail_params": {
        "enterDate": "1150326",
        "serialNumber": 6,
        "companyId": "6748",
        "marketKind": "rotc"
      },
      "detail": {
        "code": 200,
        "message": "查詢成功",
        "result": {
          "marketName": "興櫃公司",
          "companyId": "6748",
          "data": [
            [
              6,
              "115/03/26",
              "19:46:48",
              "謝達仁",
              "總經理",
              "07-6955569",
              "公告本公司董事會通過擬辦理現金增資供初次上市(櫃)或臺灣\r\n創新板有價證券之上市前公開承銷暨原股東全數放棄認購案",
              "9",
              "115/03/26",
              "1.董事會決議日期:115/03/26\n2.增資資金來源:現金增資\n3.發行股數(如屬盈餘或公積轉增資，則不含配發給員工部分):未定。\n4.每股面額:新台幣10元。\n5.發行總金額:未定。\n6.發行價格:未定。\n7.員工認購股數或配發金額:依公司法第267條規定，\n保留現金增資發行新股總數10%~15%之股數由員工認購。\n8.公開銷售股數:未定。\n9.原股東認購或無償配發比例(請註明暫定每仟股認購或配發股數):除保留員工認購\n外，其餘85%~90%由原股東優先認購部分，擬依證券交易法28條之1規定及相關法令\n規定，不受公司法第267條第三項關於原股東優先認購規定之限制，全數委由證券\n承銷商辦理公開承銷之用。\n10.畸零股及逾期未認購股份之處理方式:擬授權董事長洽特定人按發行價格認購。\n11.本次發行新股之權利義務:與原已發行普通股相同。\n12.本次增資資金用途:供本公司初次上櫃前公開承銷之股份來源。\n13.其他應敘明事項:本次現金增資之發行價格、發行條件、實際發行數量、承銷方\n式、計畫項目、募集金額、預計進度及可能產生效益等相關事項，暨其他一切有關\n發行計畫之事宜，或因主管機關核定之內容、法令變更及基於管理評估或客觀條件\n需要修正時，擬提請股東會授權董事會全權處理之。"
            ]
          ],
          "footer": [
            "以上資料均由各公司依發言當時所屬市場別之規定申報後，由本系統對外公佈，資料如有虛偽不實，均由該公司負責。"
          ],
          "header": {
            "note": [],
            "subTitle": [],
            "mainTitle": [
              "公司當日重大訊息之詳細內容"
            ]
          },
          "titles": [
            {
              "main": "序號",
              "sub": []
            },
            {
              "main": "發言日期",
              "sub": []
            },
            {
              "main": "發言時間",
              "sub": []
            },
            {
              "main": "發言人",
              "sub": []
            },
            {
              "main": "發言人職稱",
              "sub": []
            },
            {
              "main": "發言人電話",
              "sub": []
            },
            {
              "main": "主旨",
              "sub": []
            },
            {
              "main": "符合條款",
              "sub": []
            },
            {
              "main": "事實發生日",
              "sub": []
            },
            {
              "main": "說明",
              "sub": []
            }
          ],
          "companyAbbreviation": "亞果生醫"
        },
        "datetime": "115/03/27 04:36:15"
      },
      "fetched_at_tw": "2026-03-27 04:36:10"
    },
    {
      "key": "1150326|rotc|6920|9",
      "speech_date": "115/03/26",
      "speech_time": "19:49:47",
      "company_id": "6920",
      "company_name": "恆勁科技",
      "subject": "公告本公司董事會決議不繼續辦理114年度股東常會通過之私募普通股案",
      "matched_keywords": [
        "私募普通股"
      ],
      "detail_params": {
        "enterDate": "1150326",
        "serialNumber": 9,
        "companyId": "6920",
        "marketKind": "rotc"
      },
      "detail": {
        "code": 200,
        "message": "查詢成功",
        "result": {
          "marketName": "興櫃公司",
          "companyId": "6920",
          "data": [
            [
              9,
              "115/03/26",
              "19:49:47",
              "許詩濱",
              "營運長",
              "(03)598-5778",
              "公告本公司董事會決議不繼續辦理114年度股東常會通過之\r\n私募普通股案",
              "14",
              "115/03/26",
              "1.董事會決議變更日期:115/03/26\n2.原計畫申報生效之日期:NA\n3.變動原因:本公司經114/06/30股東常會決議通過，以不超過50,000,000股額度內，\n以私募方式辦理現金增資發行普通股，並授權董事會\n於股東常會決議之日起一年內全數或分二次辦理，現因期限將屆，\n董事會決議於剩餘期限內不繼續辦理。\n4.歷次變更前後募集資金計畫:不適用。\n5.預計執行進度:不適用。\n6.預計完成日期:不適用。\n7.預計可能產生效益:不適用。\n8.與原預計效益產生之差異:不適用。\n9.本次變更對股東權益之影響:不適用。\n10.原主辦承銷商評估意見摘要:不適用。\n11.其他應敘明事項:本案經董事會決議通過後，提請115年股東常會報告。"
            ]
          ],
          "footer": [
            "以上資料均由各公司依發言當時所屬市場別之規定申報後，由本系統對外公佈，資料如有虛偽不實，均由該公司負責。"
          ],
          "header": {
            "note": [],
            "subTitle": [],
            "mainTitle": [
              "公司當日重大訊息之詳細內容"
            ]
          },
          "titles": [
            {
              "main": "序號",
              "sub": []
            },
            {
              "main": "發言日期",
              "sub": []
            },
            {
              "main": "發言時間",
              "sub": []
            },
            {
              "main": "發言人",
              "sub": []
            },
            {
              "main": "發言人職稱",
              "sub": []
            },
            {
              "main": "發言人電話",
              "sub": []
            },
            {
              "main": "主旨",
              "sub": []
            },
            {
              "main": "符合條款",
              "sub": []
            },
            {
              "main": "事實發生日",
              "sub": []
            },
            {
              "main": "說明",
              "sub": []
            }
          ],
          "companyAbbreviation": "恆勁科技"
        },
        "datetime": "115/03/27 04:36:15"
      },
      "fetched_at_tw": "2026-03-27 04:36:10"
    }
  ]
}